{
  "$schema": "https://schema.tauri.app/config/2",
  "productName": "Smart Reader",
  "version": "0.1.0",
  "identifier": "com.smartreader.desktop",
  "build": {
    "beforeDevCommand": {
      "cwd": "..",
      "script": "npm run dev"
    },
    "beforeBuildCommand": {
      "cwd": "..",
      "script": "npm run build"
    },
    "devUrl": "http://localhost:1420",
    "frontendDist": "../dist"
  },
  "app": {
    "withGlobalTauri": false,
    "windows": [
      {
        "label": "main",
        "title": "Smart Reader",
        "width": 1400,
        "height": 900,
        "resizable": true
      }
    ],
    "security": {
      "csp": null
    }
  },
  "bundle": {
    "active": true,
    "targets": "all"
  }
}
